mytor/__init__.py
mytor/client.py
mytor/connections.py
mytor/cursor.py
mytor/pool.py
mytor/util.py
mytor-0.2.7.dist-info/DESCRIPTION.rst
mytor-0.2.7.dist-info/METADATA
mytor-0.2.7.dist-info/metadata.json
mytor-0.2.7.dist-info/RECORD
mytor-0.2.7.dist-info/top_level.txt
mytor-0.2.7.dist-info/WHEEL
