Metadata-Version: 2.0
Name: mytor
Version: 0.2.7
Summary: Tornado asynchronous MySQL Driver [fork of TorMysql]
Home-page: https://github.com/mosquito/mytor
Author: ['snower', 'mosquito']
Author-email: ['sujian199@gmail.com', 'me@mosquito.su']
License: MIT
Keywords: tornado,mysql
Platform: UNKNOWN
Requires-Dist: tornado (>=4.1)
Requires-Dist: PyMySQL (==0.6.7)
Requires-Dist: greenlet (>=0.4.2)
